expsolve/__init__.py
expsolve/discretize/__init__.py
expsolve/discretize/spatial.py
expsolve/discretize/graphs/__init__.py
expsolve/discretize/graphs/graph.py
expsolve/discretize/graphs/visualize.py
expsolve/discretize/tensorgrid/__init__.py
expsolve/discretize/tensorgrid/fourier.py
expsolve/discretize/tensorgrid/grid.py
expsolve/discretize/tensorgrid/operators.py
expsolve/discretize/tensorgrid/spectral.py
expsolve/discretize/tensorgrid/visualize.py
expsolve/evolve/__init__.py
expsolve/evolve/animation.py
expsolve/evolve/timepropagation.py
expsolve/evolve/splittings/__init__.py
expsolve/evolve/splittings/classical.py
expsolve/linalg/__init__.py
expsolve/linalg/matrices.py
expsolve/utils/__init__.py
expsolve/utils/colors.py
expsolve/utils/datatypes.py
expsolve/utils/files.py
expsolve/utils/functionals.py
expsolve/utils/ot.csv
expsolve-0.1.7.dist-info/METADATA
expsolve-0.1.7.dist-info/WHEEL
expsolve-0.1.7.dist-info/licenses/LICENSE.md
expsolve-0.1.7.dist-info/RECORD
