Metadata-Version: 2.3
Name: expsolve
Version: 0.1.7
Summary: A PyTorch compatible Differentiable Numerical Algorithms package for computational quantum mechanics
Project-URL: Homepage, https://github.com/brownadder/expsolve
Project-URL: Bug Tracker, https://github.com/brownadder/expsolve
Author-email: Pranav Singh <ps2106@bath.ac.uk>
Maintainer-email: Pranav Singh <ps2106@bath.ac.uk>
License: MIT
License-File: LICENSE.md
Keywords: PDE,dispersive,exponential,fourier,integrator,quantum,splitting
Classifier: License :: OSI Approved :: MIT License
Classifier: Operating System :: OS Independent
Classifier: Programming Language :: Python :: 3
Classifier: Topic :: Scientific/Engineering :: Physics
Requires-Python: >=3.7
Requires-Dist: numpy>=1.16.5
Requires-Dist: torch>=1.13.1
